gcd_calculator/__init__.py
gcd_calculator/gcd.py
gcd_calculator-0.2.0.dist-info/LICENSE
gcd_calculator-0.2.0.dist-info/METADATA
gcd_calculator-0.2.0.dist-info/WHEEL
gcd_calculator-0.2.0.dist-info/top_level.txt
gcd_calculator-0.2.0.dist-info/RECORD
