Metadata-Version: 2.1
Name: gcd_calculator
Version: 0.2.0
Summary: GCD Calculator
Home-page: https://github.com/webbro-software/gcd-calculator
Author: Usmonov Shoxruxmirzo
Author-email: usmonovshohruxmirzo@gmail.com
Classifier: Programming Language :: Python :: 3
Classifier: License :: OSI Approved :: MIT License
Classifier: Operating System :: OS Independent
Requires-Python: >=3.6
License-File: LICENSE
